README.md
setup.py
pphw_utils/__init__.py
pphw_utils/records.py
pphw_utils.egg-info/PKG-INFO
pphw_utils.egg-info/SOURCES.txt
pphw_utils.egg-info/dependency_links.txt
pphw_utils.egg-info/top_level.txt
test/__init__.py
test/test_records.py