Metadata-Version: 2.1
Name: pphw-utils
Version: 1.0.0
Summary: Utilities for records pipeline processing
Home-page: https://github.com/mew-www/xy-pphw-utils
Author: Miy
Author-email: mew.proxy@hotmail.com
Classifier: Programming Language :: Python :: 3
Classifier: Programming Language :: Python :: 3.8
Classifier: Operating System :: OS Independent
